job_helper/Job.py
job_helper/Status.py
job_helper/job_extension.py
job_helper-1.2.dist-info/METADATA
job_helper-1.2.dist-info/WHEEL
job_helper-1.2.dist-info/top_level.txt
job_helper-1.2.dist-info/RECORD
