Metadata-Version: 2.1
Name: job-helper
Version: 1.2
Summary: An async job system using RabbitMQ & CloudEvents
Author: Inuits
Author-email: developers@inuits.eu
License: GPLv2
Classifier: License :: OSI Approved :: GNU General Public License v2 (GPLv2)
Classifier: Intended Audience :: Developers
Classifier: Programming Language :: Python :: 3
Provides: job_helper
Requires-Dist: cloudevents (>=1.4.0)
Requires-Dist: Flask (>=1.1.2)
Requires-Dist: rabbitmq-pika-flask (>=1.2.15)
